{
    "Distribution": "2n",
    "LambdaForEgoism": 0.0,
    "MultilevelDeath1Percent": 0.0,
    "NumberOfCells": 100,
    "NumberOfRsrcsInEachCell": 1000,
    "consume": "independent",
    "initFile": "E3a",
    "numGen": 300,
    "outDir": null,
    "outFName": null,
    "saveExcel": false,
    "setRandomSeed": -1,
    "species": [
        {
            "AssociatedSpecies": "MG",
            "DirectOffspring": 0,
            "Distribution": "2n",
            "FitnessVariationLimit": 1,
            "GroupPartner": "",
            "IndirectOffspring": 2,
            "NumberOfItems": 49816,
            "PhenotypicFlexibility": 0.0,
            "id": "AAs"
        },
        {
            "AssociatedSpecies": "AAs",
            "DirectOffspring": 0,
            "Distribution": "2n",
            "FitnessVariationLimit": 1,
            "GroupPartner": "",
            "IndirectOffspring": 2,
            "NumberOfItems": 50184,
            "PhenotypicFlexibility": 0.0,
            "id": "MG"
        }
    ],
    "varia": false,
    "verbose": true
}